ifem_to_vt/__init__.py
ifem_to_vt/__main__.py
ifem_to_vt/fields.py
ifem_to_vt/geometry.py
ifem_to_vt/pipeline.py
ifem_to_vt/typing.py
ifem_to_vt/util.py
ifem_to_vt/reader/__init__.py
ifem_to_vt/reader/ifem.py
ifem_to_vt/reader/puregeometry.py
ifem_to_vt/reader/reader.py
ifem_to_vt/reader/simra.py
ifem_to_vt/reader/wrf.py
ifem_to_vt/writer/__init__.py
ifem_to_vt/writer/nc.py
ifem_to_vt/writer/vtf.py
ifem_to_vt/writer/vtk.py
ifem_to_vt/writer/writer.py
IFEM_to_VT-2.0.2.dist-info/LICENSE
IFEM_to_VT-2.0.2.dist-info/METADATA
IFEM_to_VT-2.0.2.dist-info/WHEEL
IFEM_to_VT-2.0.2.dist-info/entry_points.txt
IFEM_to_VT-2.0.2.dist-info/top_level.txt
IFEM_to_VT-2.0.2.dist-info/RECORD
