Metadata-Version: 2.1
Name: IFEM-to-VT
Version: 2.0.2
Summary: Convert between different mesh data formats
Home-page: UNKNOWN
Maintainer: Eivind Fonn
Maintainer-email: eivind.fonn@sintef.no
License: UNKNOWN
Platform: UNKNOWN
Requires-Dist: click
Requires-Dist: dataclasses
Requires-Dist: numpy
Requires-Dist: Splipy (>=1.4)
Requires-Dist: lrsplines (>=1.5)
Requires-Dist: h5py
Requires-Dist: vtk
Requires-Dist: netcdf4
Requires-Dist: nptyping
Requires-Dist: singledispatchmethod
Requires-Dist: treelog
Provides-Extra: vtf
Requires-Dist: vtfwriter ; extra == 'vtf'
Provides-Extra: deploy
Requires-Dist: twine ; extra == 'deploy'
Requires-Dist: cibuildwheel (==1.1.0) ; extra == 'deploy'
Provides-Extra: testing
Requires-Dist: pytest ; extra == 'testing'
